langchain_dev_utils/__init__.py
langchain_dev_utils/_utils.py
langchain_dev_utils/py.typed
langchain_dev_utils/agents/__init__.py
langchain_dev_utils/agents/factory.py
langchain_dev_utils/agents/file_system.py
langchain_dev_utils/agents/plan.py
langchain_dev_utils/agents/wrap.py
langchain_dev_utils/agents/middleware/__init__.py
langchain_dev_utils/agents/middleware/format_prompt.py
langchain_dev_utils/agents/middleware/handoffs.py
langchain_dev_utils/agents/middleware/model_fallback.py
langchain_dev_utils/agents/middleware/model_router.py
langchain_dev_utils/agents/middleware/plan.py
langchain_dev_utils/agents/middleware/summarization.py
langchain_dev_utils/agents/middleware/tool_call_repair.py
langchain_dev_utils/agents/middleware/tool_emulator.py
langchain_dev_utils/agents/middleware/tool_selection.py
langchain_dev_utils/chat_models/__init__.py
langchain_dev_utils/chat_models/base.py
langchain_dev_utils/chat_models/types.py
langchain_dev_utils/chat_models/adapters/__init__.py
langchain_dev_utils/chat_models/adapters/create_utils.py
langchain_dev_utils/chat_models/adapters/openai_compatible.py
langchain_dev_utils/chat_models/adapters/register_profiles.py
langchain_dev_utils/embeddings/__init__.py
langchain_dev_utils/embeddings/base.py
langchain_dev_utils/embeddings/adapters/__init__.py
langchain_dev_utils/embeddings/adapters/create_utils.py
langchain_dev_utils/embeddings/adapters/openai_compatible.py
langchain_dev_utils/message_convert/__init__.py
langchain_dev_utils/message_convert/content.py
langchain_dev_utils/message_convert/format.py
langchain_dev_utils/pipeline/__init__.py
langchain_dev_utils/pipeline/parallel.py
langchain_dev_utils/pipeline/sequential.py
langchain_dev_utils/pipeline/types.py
langchain_dev_utils/tool_calling/__init__.py
langchain_dev_utils/tool_calling/human_in_the_loop.py
langchain_dev_utils/tool_calling/utils.py
langchain_dev_utils-1.3.7.dist-info/METADATA
langchain_dev_utils-1.3.7.dist-info/WHEEL
langchain_dev_utils-1.3.7.dist-info/licenses/LICENSE
langchain_dev_utils-1.3.7.dist-info/RECORD
