Metadata-Version: 2.4
Name: langchain-dev-utils
Version: 1.3.7
Summary: A practical utility library for LangChain and LangGraph development
Project-URL: Source Code, https://github.com/TBice123123/langchain-dev-utils
Project-URL: repository, https://github.com/TBice123123/langchain-dev-utils
Project-URL: documentation, https://tbice123123.github.io/langchain-dev-utils
Author-email: tiebingice <tiebingice123@outlook.com>
License-File: LICENSE
Requires-Python: >=3.11
Requires-Dist: langchain-core>=1.2.5
Requires-Dist: langchain>=1.2.0
Requires-Dist: langgraph>=1.0.0
Provides-Extra: standard
Requires-Dist: json-repair>=0.53.1; extra == 'standard'
Requires-Dist: langchain-openai; extra == 'standard'
